xe2layout/__init__.py
xe2layout/config.py
xe2layout/inoutstream.py
xe2layout/release.py
xe2layout/template.py
xe2layout/xenon2layout.py
xe2layout/templates/readme.md.j2
xe2layout/templates/template_conf.yml.j2
xe2layout-2020.5.26.dist-info/LICENSE.md
xe2layout-2020.5.26.dist-info/METADATA
xe2layout-2020.5.26.dist-info/WHEEL
xe2layout-2020.5.26.dist-info/entry_points.txt
xe2layout-2020.5.26.dist-info/top_level.txt
xe2layout-2020.5.26.dist-info/RECORD
