Metadata-Version: 2.1
Name: xe2layout
Version: 2020.5.26
Summary: UNKNOWN
Home-page: https://gitlab.com/guichet-entreprises.fr/libs/layout
Author: Christian Cougourdan
Author-email: florent.tournois@gmail.com
License: MIT
Platform: UNKNOWN
Classifier: Programming Language :: Python
Classifier: Operating System :: OS Independent
Classifier: Programming Language :: Python :: 3
Classifier: Programming Language :: Python :: 3.5
Requires-Dist: pymdtools
Requires-Dist: pyyaml
Requires-Dist: beautifulsoup4
Requires-Dist: jinja2
Requires-Dist: html5lib
Requires-Dist: md2py
Requires-Dist: polib
Requires-Dist: appdirs
Requires-Dist: upref
Requires-Dist: python-gitlab
Requires-Dist: pdfkit
Requires-Dist: PyPDF2
Requires-Dist: url-normalize
Requires-Dist: requests
